[{
    "id": 0,
    "fname": "Василий",
    "surname": "Иванов",
    "birthday": "10/08/1991",
    "patronymic": "Иванович"
  },{
    "id": 1,
    "fname": "Вася",
    "surname": "Иванов",
    "birthday": "10/08/1991",
    "patronymic": "Иванович"
  }, {
    "id": 2,
    "fname": "Петя",
    "surname": "Федоров",
    "birthday": "03/08/1993",
    "patronymic": "Федdорович"
  }, {
    "id": 3,
    "fname": "Альберт",
    "surname": "Федоров",
    "birthday": "03/08/1993",
    "patronymic": "Феdдорович"
  }, {
    "id": 4,
    "fname": "Сергей",
    "surname": "Федоров",
    "birthday": "03/08/1993",
    "patronymic": "Федороdвич"
  }, {
    "id": 5,
    "fname": "Челик",
    "surname": "Федоров",
    "birthday": "03/08/1993",
    "patronymic": "Федорович"
  }, {
    "id": 6,
    "fname": "Катя",
    "surname": "Федоров",
    "birthday": "03/08/1993",
    "patronymic": "Федорович"
  }, {
    "id": 7,
    "fname": "Маша",
    "surname": "Федоров",
    "birthday": "03/08/1993",
    "patronymic": "Федорович"
  }, {
    "id": 8,
    "fname": "Олег",
    "surname": "Федоров",
    "birthday": "03/08/1993",
    "patronymic": "Федорович"
  }, {
    "id": 9,
    "fname": "Тьяго",
    "surname": "Федоров",
    "birthday": "03/08/1993",
    "patronymic": "Федорович"
  }, {
    "id": 10,
    "fname": "Владимир",
    "surname": "Федоров",
    "birthday": "03/08/1993",
    "patronymic": "Федорович"
  }, {
    "id": 11,
    "fname": "Тимур",
    "surname": "Федоров",
    "birthday": "03/08/1993",
    "patronymic": "Федорович"
  }, {
    "id": 12,
    "fname": "Булат",
    "surname": "Федоров",
    "birthday": "03/08/1993",
    "patronymic": "Федорович"
  }, {
    "id": 13,
    "fname": "Константин",
    "surname": "Федоров",
    "birthday": "03/08/1993",
    "patronymic": "Федорович"
  }, {
    "id": 14,
    "fname": "Амир",
    "surname": "Федоров",
    "birthday": "03/08/1993",
    "patronymic": "Федорович"
  }, {
    "id": 15,
    "fname": "Таня",
    "surname": "Федоров",
    "birthday": "03/08/1993",
    "patronymic": "Федорович"
  }]